phis_build/__main__.py
phis_build/args.py
phis_build/build_steps.py
phis_build/build_zipapp.py
phis_build/config.py
phis_build/get_args.py
phis_build/logging_config.py
phis_build/main.py
phis_build/run_template.bat
phis_build/version.py
phis_build-2025.11.7.1.dist-info/METADATA
phis_build-2025.11.7.1.dist-info/WHEEL
phis_build-2025.11.7.1.dist-info/entry_points.txt
phis_build-2025.11.7.1.dist-info/licenses/LICENSE
phis_build-2025.11.7.1.dist-info/RECORD
