Metadata-Version: 2.4
Name: phis-build
Version: 2025.11.7.1
Summary: custom build system
License-File: LICENSE
Requires-Python: >=3.8
Requires-Dist: pydantic>=2.10.6
Requires-Dist: pyinstaller>=6.14.2
Requires-Dist: toml>=0.10.2
Requires-Dist: tomli>=2.2.1
Requires-Dist: tqdm>=4.67.1
